{
    "$schema": "https://mintlify.com/docs.json",
    "theme": "mint",
    "name": "baobao docs",
    "description": "documentation for baobao",
    "colors": {
        "primary": "#e57a9e",
        "light": "#f7c0d0",
        "dark": "#d44d76"
    },
    "seo": {
        "metatags": {
            "theme-color": "#e3c2cd",
            "og:site_name": "baobao.dev"
        }
    },
    "navigation": {
        "groups": [
            {
                "group": "Overview",
                "pages": [
                    "introduction"
                ]
            },
            {
                "group": "Server Commands",
                "pages": [
                    "features/giveaway",
                    {
                        "group": "Admin Server",
                        "icon": "lock",
                        "pages": ["features/moderation/purge"]
                    }
                ]
            },
            {
                "group": "Resources",
                "pages": [
                    "resources/message_id",
                    "resources/syntax"
                ]
            }
        ]
    },
    "favicon": "favicon.png",
    "navbar": {
        "links": [
            {
                "label": "Support Server",
                "href": "https://discord.gg/AXRShswtZ4"
            }
        ]
    },
    "footer": {
        "socials": {
            "discord": "https://discord.gg/AXRShswtZ4",
            "github": "https://github.com/bao-bun"
        }
    }
}